odoo/addons/es_address_format_simplified/__init__.py
odoo/addons/es_address_format_simplified/__manifest__.py
odoo/addons/es_address_format_simplified/data/res_country_data.xml
odoo/addons/es_address_format_simplified/models/__init__.py
odoo/addons/es_address_format_simplified/models/address_format_es_simplified.py
odoo12_addon_es_address_format_simplified-12.0.0.0.3.dist-info/METADATA
odoo12_addon_es_address_format_simplified-12.0.0.0.3.dist-info/WHEEL
odoo12_addon_es_address_format_simplified-12.0.0.0.3.dist-info/top_level.txt
odoo12_addon_es_address_format_simplified-12.0.0.0.3.dist-info/RECORD
