Metadata-Version: 2.1
Name: odoo12-addon-es-address-format-simplified
Version: 12.0.0.0.3
Summary: Address format for Spain with no country and address in one line
Home-page: http://www.coopdevs.org
Author: Coopdevs SCCL
License: AGPL-3
Platform: UNKNOWN
Classifier: Programming Language :: Python
Classifier: Framework :: Odoo
Classifier: License :: OSI Approved :: GNU Affero General Public License v3
Requires-Python: >=3.5
Requires-Dist: odoo (<12.1dev,>=12.0a)
